libgolf/__init__.py
libgolf/list.py
libgolf/string.py
libgolf/vectorise.py
libgolf-0.0.3.post1.dist-info/WHEEL
libgolf-0.0.3.post1.dist-info/METADATA
libgolf-0.0.3.post1.dist-info/RECORD
