Metadata-Version: 2.1
Name: libgolf
Version: 0.0.3.post1
Summary: Common utilities for implementing golfing language builtin libraries
Home-page: https://github.com/pxeger/libgolf
License: Artistic-2.0
Author: pxeger
Author-email: _@pxeger.com
Requires-Python: >=3.10,<4.0
Classifier: Development Status :: 3 - Alpha
Classifier: Intended Audience :: Developers
Classifier: License :: OSI Approved :: Artistic License
Classifier: Programming Language :: Python :: 3
Classifier: Programming Language :: Python :: 3.10
Classifier: Topic :: Software Development :: Libraries
Classifier: Topic :: Utilities
Project-URL: Repository, https://github.com/pxeger/libgolf
